SceneEditor/SceneEditor.py
SceneEditor/__init__.py
SceneEditor/GUI/MainView.py
SceneEditor/GUI/MenuBar.py
SceneEditor/GUI/ToolBar.py
SceneEditor/GUI/__init__.py
SceneEditor/GUI/dialogs/ShaderInput.py
SceneEditor/GUI/dialogs/ShaderLoaderDialog.py
SceneEditor/GUI/dialogs/ShaderLoaderDialogManager.py
SceneEditor/GUI/dialogs/__init__.py
SceneEditor/GUI/panels/ObjectPropertiesDefinition.py
SceneEditor/GUI/panels/PropertiesPanel.py
SceneEditor/GUI/panels/StructurePanel.py
SceneEditor/GUI/panels/__init__.py
SceneEditor/core/CameraController.py
SceneEditor/core/Core.py
SceneEditor/core/CoreKillRingHandler.py
SceneEditor/core/KillRing.py
SceneEditor/core/SelectionHandler.py
SceneEditor/core/TransformationHandler.py
SceneEditor/core/__init__.py
SceneEditor/directGuiOverrides/DirectOptionMenu.py
SceneEditor/directGuiOverrides/__init__.py
SceneEditor/directtoolsOverrides/DirectGrid.py
SceneEditor/directtoolsOverrides/__init__.py
SceneEditor/export/ExportBam.py
SceneEditor/export/ExportProject.py
SceneEditor/export/ExportPy.py
SceneEditor/export/__init__.py
SceneEditor/icons/ArrowDownSmall.png
SceneEditor/icons/ArrowUpSmall.png
SceneEditor/icons/Collapse.png
SceneEditor/icons/Collapsed.png
SceneEditor/icons/CycleRedo.png
SceneEditor/icons/Delete.png
SceneEditor/icons/DeleteSmall.png
SceneEditor/icons/Export.png
SceneEditor/icons/GridOff.png
SceneEditor/icons/GridOn.png
SceneEditor/icons/Help.png
SceneEditor/icons/Load.png
SceneEditor/icons/New.png
SceneEditor/icons/Quit.png
SceneEditor/icons/Redo.png
SceneEditor/icons/Reload.png
SceneEditor/icons/Save.png
SceneEditor/icons/Settings.png
SceneEditor/icons/Undo.png
SceneEditor/icons/VisibilityOffSmall.png
SceneEditor/icons/VisibilityOnSmall.png
SceneEditor/loader/LoadProject.py
SceneEditor/loader/__init__.py
SceneEditor/tools/JSONTools.py
SceneEditor/tools/__init__.py
SceneEditor-22.5.dist-info/LICENSE
SceneEditor-22.5.dist-info/METADATA
SceneEditor-22.5.dist-info/WHEEL
SceneEditor-22.5.dist-info/top_level.txt
SceneEditor-22.5.dist-info/RECORD
