Metadata-Version: 2.1
Name: SceneEditor
Version: 22.5
Summary: A scene editor for the Panda3D engine
Home-page: https://github.com/fireclawthefox/SceneEditor
Author: Fireclaw
Author-email: fireclawthefox@gmail.com
Classifier: Programming Language :: Python :: 3
Classifier: License :: OSI Approved :: BSD License
Classifier: Operating System :: OS Independent
Classifier: Development Status :: 2 - Pre-Alpha
Classifier: Intended Audience :: Developers
Classifier: Intended Audience :: End Users/Desktop
Classifier: Topic :: Artistic Software
Classifier: Topic :: Multimedia :: Graphics
Classifier: Topic :: Multimedia :: Graphics :: Editors
Requires-Python: >=3.6
License-File: LICENSE
Requires-Dist: panda3d
Requires-Dist: DirectFolderBrowser
Requires-Dist: DirectGuiExtension
